shiqi_grafana_chart_mcp/__init__.py
shiqi_grafana_chart_mcp-0.1.0.dist-info/METADATA
shiqi_grafana_chart_mcp-0.1.0.dist-info/WHEEL
shiqi_grafana_chart_mcp-0.1.0.dist-info/entry_points.txt
shiqi_grafana_chart_mcp-0.1.0.dist-info/RECORD
